marketsandbox/__init__.py
marketsandbox/marketsandbox.py
marketsandbox-0.0.1.dist-info/WHEEL
marketsandbox-0.0.1.dist-info/METADATA
marketsandbox-0.0.1.dist-info/RECORD
