Metadata-Version: 2.4
Name: marketsandbox
Version: 0.0.1
Summary: A market sandbox that lets you create users and buy and sell resources with both market orders and limit orders.
Author-email: Marius Facktor <mariusfacktor@gmail.com>
Requires-Python: >=3.9
Classifier: Programming Language :: Python :: 3
Classifier: License :: OSI Approved :: MIT License
Classifier: Operating System :: OS Independent
Requires-Dist: requests>2.32
Project-URL: Homepage, https://github.com/mariusfacktor/market_simulator
Project-URL: Issues, https://github.com/mariusfacktor/market_simulator/issues
